setup.py
platonic_solids_isma/__init__.py
platonic_solids_isma/measures.py
platonic_solids_isma/parts.py
platonic_solids_isma/radius.py
platonic_solids_isma.egg-info/PKG-INFO
platonic_solids_isma.egg-info/SOURCES.txt
platonic_solids_isma.egg-info/dependency_links.txt
platonic_solids_isma.egg-info/not-zip-safe
platonic_solids_isma.egg-info/top_level.txt