Metadata-Version: 2.1
Name: platonic-solids-isma
Version: 0.0
Summary: solidos platonicos de Gonzalo
Author-email: iahmadrab10@gmail.com
License: UNKNOWN
Platform: UNKNOWN
